pyuba/__init__.py
pyuba/calc/__init__.py
pyuba/calc/acquisition.py
pyuba/calc/bayesian.py
pyuba/calc/frequentist.py
pyuba/calc/funnel.py
pyuba/calc/retention.py
pyuba/calc/user_journey.py
pyuba/calc/utils.py
pyuba/data/__init__.py
pyuba/data/make_dataset.py
pyuba/visualizations/__init__.py
pyuba/visualizations/funnel_plots.py
pyuba/visualizations/growth.py
pyuba/visualizations/retention_plots.py
pyuba/visualizations/user_journey_plots.py
pyuba-0.1.0.dist-info/LICENSE
pyuba-0.1.0.dist-info/METADATA
pyuba-0.1.0.dist-info/WHEEL
pyuba-0.1.0.dist-info/top_level.txt
pyuba-0.1.0.dist-info/RECORD
