Metadata-Version: 2.1
Name: pyuba
Version: 0.1.0
Summary: growth hacking tool test
Home-page: https://growth-dashboard.herokuapp.com/
Author: Wook Lee
Author-email: leewook94@gmail.com
License: UNKNOWN
Keywords: growth-hacking,visualization,data-analysis
Platform: UNKNOWN
Classifier: Programming Language :: Python :: 3
Classifier: License :: OSI Approved :: Apache Software License
Classifier: Operating System :: OS Independent
License-File: LICENSE
Requires-Dist: numpy
Requires-Dist: pandas
Requires-Dist: matplotlib
Requires-Dist: seaborn
Requires-Dist: plotly
Requires-Dist: scipy
